<?xml version="1.0" ?><annotation>
	<folder>cam11</folder>
	<filename>000499.jpg</filename>
	<path>/home/zhaohuaqing/Documents/4_2/images/000499.jpg</path>
	<source>
		<database>Unknown</database>
	</source>
	<size>
		<width>1280</width>
		<height>720</height>
		<depth>3</depth>
	</size>
	<segmented>0</segmented>
	<object>
		<name>green</name>
		<pose>Unspecified</pose>
		<truncated>0</truncated>
		<difficult>0</difficult>
		<bndbox>
			<xmin>946</xmin>
			<ymin>613</ymin>
			<xmax>967</xmax>
			<ymax>660</ymax>
		</bndbox>
	</object>
	<object>
		<name>off</name>
		<pose>Unspecified</pose>
		<truncated>0</truncated>
		<difficult>0</difficult>
		<bndbox>
			<xmin>555</xmin>
			<ymin>638</ymin>
			<xmax>576</xmax>
			<ymax>680</ymax>
		</bndbox>
	</object>
</annotation>