<?xml version="1.0" ?><annotation verified="yes">
	<folder>cam11</folder>
	<filename>000693.jpg</filename>
	<path>/home/zhaohuaqing/Documents/4_2/images/000693.jpg</path>
	<source>
		<database>Unknown</database>
	</source>
	<size>
		<width>1280</width>
		<height>720</height>
		<depth>3</depth>
	</size>
	<segmented>0</segmented>
	<object>
		<name>green</name>
		<pose>Unspecified</pose>
		<truncated>0</truncated>
		<difficult>0</difficult>
		<bndbox>
			<xmin>892</xmin>
			<ymin>261</ymin>
			<xmax>954</xmax>
			<ymax>382</ymax>
		</bndbox>
	</object>
	<object>
		<name>green</name>
		<pose>Unspecified</pose>
		<truncated>0</truncated>
		<difficult>0</difficult>
		<bndbox>
			<xmin>1114</xmin>
			<ymin>256</ymin>
			<xmax>1168</xmax>
			<ymax>372</ymax>
		</bndbox>
	</object>
</annotation>